{
  "hash": "7b151692",
  "configHash": "bb2d39f2",
  "lockfileHash": "51f9d067",
  "browserHash": "1c033f86",
  "optimized": {
    "@vue/devtools-api": {
      "src": "../../../../node_modules/.pnpm/@vue+devtools-api@7.7.7/node_modules/@vue/devtools-api/dist/index.js",
      "file": "@vue_devtools-api.js",
      "fileHash": "d81c76cf",
      "needsInterop": false
    },
    "@vuepress/shared": {
      "src": "../../../../node_modules/.pnpm/@vuepress+shared@2.0.0-rc.24/node_modules/@vuepress/shared/dist/index.js",
      "file": "@vuepress_shared.js",
      "fileHash": "f7038fba",
      "needsInterop": false
    },
    "vue": {
      "src": "../../../../node_modules/.pnpm/vue@3.5.18/node_modules/vue/dist/vue.runtime.esm-bundler.js",
      "file": "vue.js",
      "fileHash": "30d57c8a",
      "needsInterop": false
    },
    "vue-router": {
      "src": "../../../../node_modules/.pnpm/vue-router@4.5.1_vue@3.5.18/node_modules/vue-router/dist/vue-router.esm-bundler.js",
      "file": "vue-router.js",
      "fileHash": "e73c47fc",
      "needsInterop": false
    }
  },
  "chunks": {
    "chunk-7X4VNE2G": {
      "file": "chunk-7X4VNE2G.js"
    }
  }
}